[
    {
      "comment": "Great article! I learned a lot about closures."
    },
    {
      "comment": "This was really helpful. Thanks for sharing!"
    },
    {
      "comment": "Flexbox vs. Grid has always confused me. This cleared things up!"
    },
    {
      "comment": "Web performance optimization is so underrated. Great insights!"
    },
    {
      "comment": "Can't wait to see what the future holds for web dev!"
    },
    {
      "comment": "React Hooks have been a game changer for my projects."
    },
    {
      "comment": "Thanks for breaking this down so clearly!"
    },
    {
      "comment": "CSS Grid is my go-to for complex layouts now."
    },
    {
      "comment": "Optimizing images has made a huge difference for my site speed."
    },
    {
      "comment": "Great explanation on useEffect—it's so versatile!"
    }
  ]